instascrap/__init__.py
instascrap/main.py
instascrap-1.1.dist-info/METADATA
instascrap-1.1.dist-info/WHEEL
instascrap-1.1.dist-info/top_level.txt
instascrap-1.1.dist-info/RECORD
