Metadata-Version: 2.1
Name: instascrap
Version: 1.1
Summary: nstascrap is a Python module for scraping Instagram profile data.
Author: Yousseif Muhammed
Author-email: me@usif.tech
License: MIT
Classifier: License :: OSI Approved :: MIT License
Classifier: Programming Language :: Python :: 3
Classifier: Programming Language :: Python :: 3.6
Classifier: Programming Language :: Python :: 3.7
Classifier: Programming Language :: Python :: 3.8
Classifier: Programming Language :: Python :: 3.9
Requires-Dist: apify-client
